nanohubremote/__init__.py
nanohubremote/_version.py
nanohubremote/output.py
nanohubremote/params.py
nanohubremote/project.py
nanohubremote/session.py
nanohub_remote-0.1.4.dist-info/METADATA
nanohub_remote-0.1.4.dist-info/WHEEL
nanohub_remote-0.1.4.dist-info/top_level.txt
nanohub_remote-0.1.4.dist-info/RECORD
