Metadata-Version: 2.4
Name: nanohub-remote
Version: 0.1.4
Summary: A set of tools to run nanohub web apis
Home-page: https://github.com/denphi/nanohub-remote
Author: Project Jupyter contributor
Author-email: Daniel Mejia <dmejiapa@purdue.edu>
Maintainer-email: Daniel Mejia <dmejiapa@purdue.edu>
License: BSD License
Platform: Linux
Platform: Mac OS X
Platform: Windows
Requires-Dist: fs>=2.4.0
Dynamic: author
Dynamic: home-page
Dynamic: platform
Dynamic: summary
